README.md
setup.py
embixtools/dataquality.py
embixtools/errors.py
embixtools/logs.py
embixtools/main.py
embixtools/opinum_client.py
embixtools/retry.py
embixtools/schedule.py
embixtools/vpn.py
embixtools/yaml_read.py
embixtools.egg-info/PKG-INFO
embixtools.egg-info/SOURCES.txt
embixtools.egg-info/dependency_links.txt
embixtools.egg-info/requires.txt
embixtools.egg-info/top_level.txt