Metadata-Version: 1.0
Name: embixtools
Version: 1.1.1
Summary: EMBIX tools
Home-page: UNKNOWN
Author: UNKNOWN
Author-email: UNKNOWN
License: UNKNOWN
Platform: UNKNOWN
